authapi/__init__.py
authapi/admin.py
authapi/apps.py
authapi/models.py
authapi/pagination.py
authapi/permissions.py
authapi/serializers.py
authapi/urls.py
authapi/utils.py
authapi/validators.py
authapi/views.py
authapi/migrations/0001_initial.py
authapi/migrations/0002_auto_20160520_1252.py
authapi/migrations/0003_auto_20160520_1413.py
authapi/migrations/0004_auto_20160523_1442.py
authapi/migrations/0005_auto_20160523_1459.py
authapi/migrations/0006_auto_20160523_1503.py
authapi/migrations/0007_auto_20160524_1409.py
authapi/migrations/0008_auto_20160610_1248.py
authapi/migrations/0009_auto_20160610_1530.py
authapi/migrations/__init__.py
authapi/templatetags/__init__.py
authapi/templatetags/seed.py
authapi/tests/__init__.py
authapi/tests/base.py
authapi/tests/test_organizations.py
authapi/tests/test_pagination.py
authapi/tests/test_teams.py
authapi/tests/test_tokens.py
authapi/tests/test_user_permissions.py
authapi/tests/test_users.py
seed_auth_api/__init__.py
seed_auth_api/settings.py
seed_auth_api/testsettings.py
seed_auth_api/urls.py
seed_auth_api/wsgi.py
seed_auth_api-0.9.8.dist-info/LICENCE
seed_auth_api-0.9.8.dist-info/METADATA
seed_auth_api-0.9.8.dist-info/WHEEL
seed_auth_api-0.9.8.dist-info/top_level.txt
seed_auth_api-0.9.8.dist-info/RECORD
