Metadata-Version: 2.1
Name: seed-auth-api
Version: 0.9.8
Summary: Seed Auth API
Home-page: https://github.com/praekelt/seed-auth-api
Author: Praekelt.org
Author-email: dev@praekelt.org
License: BSD
Platform: UNKNOWN
Classifier: Development Status :: 4 - Beta
Classifier: Framework :: Django
Classifier: License :: OSI Approved :: BSD License
Classifier: Programming Language :: Python
Classifier: Programming Language :: Python :: 2.7
Classifier: Programming Language :: Python :: 3.4
Classifier: Programming Language :: Python :: 3.5
Classifier: Topic :: Software Development :: Libraries :: Python Modules
Requires-Dist: Django (==2.2.8)
Requires-Dist: dj-database-url (==0.4.2)
Requires-Dist: psycopg2 (==2.7.3.1)
Requires-Dist: djangorestframework (==3.9.1)
Requires-Dist: drf-extensions (==0.4.0)
Requires-Dist: djangorestframework-composed-permissions (==0.2.1)
Requires-Dist: raven (==6.10.0)
